README.md
setup.cfg
setup.py
counter_r5/__init__.py
counter_r5/elasticsearch_query.py
counter_r5/generate.py
counter_r5/reports.py
counter_r5/tests/__init__.py
counter_r5/tests/build_fixtures.py
counter_r5/tests/conftest.py
counter_r5/tests/test_elasticsearch_query.py
counter_r5/tests/test_queries.py
counter_r5/tests/test_reports.py
counter_r5_elasticsearch.egg-info/PKG-INFO
counter_r5_elasticsearch.egg-info/SOURCES.txt
counter_r5_elasticsearch.egg-info/dependency_links.txt
counter_r5_elasticsearch.egg-info/requires.txt
counter_r5_elasticsearch.egg-info/top_level.txt